ReplayTables_andnp-8.0.0.dist-info/METADATA
ReplayTables_andnp-8.0.0.dist-info/WHEEL
ReplayTables/_utils/MinMaxHeap.py
ReplayTables/_utils/jit.py
ReplayTables/_utils/SamplableSet.py
ReplayTables/_utils/__init__.py
ReplayTables/_utils/logger.py
ReplayTables/_utils/np.py
ReplayTables/_utils/RandDict.py
ReplayTables/ingress/RandomIndexer.py
ReplayTables/ingress/CircularMapper.py
ReplayTables/ingress/Trackers.py
ReplayTables/ingress/LagBuffer.py
ReplayTables/ingress/IndexMapper.py
ReplayTables/ingress/MinHeapMapper.py
ReplayTables/registry.py
ReplayTables/BackwardsReplay.py
ReplayTables/interface.py
ReplayTables/sampling/PrioritySequenceSampler.py
ReplayTables/sampling/BackwardsSampler.py
ReplayTables/sampling/PrioritySampler.py
ReplayTables/sampling/tools.py
ReplayTables/sampling/IndexSampler.py
ReplayTables/sampling/UniformSampler.py
ReplayTables/PSER.py
ReplayTables/storage/NonArrayStorage.py
ReplayTables/storage/MetadataStorage.py
ReplayTables/storage/Storage.py
ReplayTables/storage/CompressedStorage.py
ReplayTables/storage/BasicStorage.py
ReplayTables/PrototypeBuffer.py
ReplayTables/ReplayBuffer.py
ReplayTables/PER.py
ReplayTables/rust.cpython-311-darwin.so
ReplayTables_andnp-8.0.0.dist-info/RECORD
