Metadata-Version: 2.4
Name: ReplayTables-andnp
Version: 8.0.0
Classifier: Programming Language :: Rust
Classifier: Programming Language :: Python :: Implementation :: CPython
Classifier: Programming Language :: Python :: Implementation :: PyPy
Requires-Dist: discrete-dists ~=1.0
Requires-Dist: numba ~=0.57
Requires-Dist: numpy >=1.23, <3.0
Requires-Dist: scipy ~=1.9
Requires-Dist: lz4 ~=4.3.2
Requires-Dist: pip ; extra == 'dev'
Requires-Dist: ruff ; extra == 'dev'
Requires-Dist: pyright ; extra == 'dev'
Requires-Dist: commitizen ; extra == 'dev'
Requires-Dist: pre-commit ; extra == 'dev'
Requires-Dist: pytest >=7.3, <9.0 ; extra == 'dev'
Requires-Dist: pytest-benchmark ~=4.0 ; extra == 'dev'
Requires-Dist: maturin >=1.4, <1.8 ; extra == 'dev'
Provides-Extra: dev
Summary: A simple replay buffer implementation in python for sampling n-step trajectories
Author-email: Andy Patterson <andnpatterson@gmail.com>
License: MIT
Requires-Python: >=3.10, <3.13
